py3afipws/__init__.py
py3afipws/cot.py
py3afipws/iibb.py
py3afipws/nsis.py
py3afipws/padron.py
py3afipws/php.py
py3afipws/pyafipws.py
py3afipws/pyemail.py
py3afipws/pyi25.py
py3afipws/pyrece.py
py3afipws/pyrece.rsrc.py
py3afipws/rece.py
py3afipws/rece1.py
py3afipws/receb.py
py3afipws/receb1.py
py3afipws/recem.py
py3afipws/recex.py
py3afipws/recex1.py
py3afipws/sired.py
py3afipws/soap.py
py3afipws/trazafito.py
py3afipws/trazamed.py
py3afipws/trazarenpre.py
py3afipws/trazavet.py
py3afipws/utils.py
py3afipws/wdigdepfiel.py
py3afipws/ws_sr_padron.py
py3afipws/wsaa.py
py3afipws/wsbfe.py
py3afipws/wsbfev1.py
py3afipws/wscdc.py
py3afipws/wscoc.py
py3afipws/wsctgv3.py
py3afipws/wsfe.py
py3afipws/wsfev1.py
py3afipws/wsfex.py
py3afipws/wsfexv1.py
py3afipws/wsltv.py
py3afipws/wsmtx.py
py3afipws-0.10.28.dist-info/METADATA
py3afipws-0.10.28.dist-info/WHEEL
py3afipws-0.10.28.dist-info/top_level.txt
py3afipws-0.10.28.dist-info/RECORD
