Metadata-Version: 2.1
Name: py3afipws
Version: 0.10.28
Summary: pyafipws for python3
Home-page: https://github.com/odoo-mastercore/pyafipws
Author: Mastercore
Author-email: far@mastercore.net
Keywords: py3afipws,py3
Classifier: Development Status :: 4 - Beta
Classifier: Intended Audience :: Developers
Classifier: Topic :: Software Development :: Build Tools
Classifier: Programming Language :: Python :: 3
Classifier: Programming Language :: Python :: 3.2
Classifier: Programming Language :: Python :: 3.3
Classifier: Programming Language :: Python :: 3.4
